quickstep.py
setup.py
proto/NetworkCli_pb2.py
proto/NetworkCli_pb2_grpc.py
proto/__init__.py
quickstep.egg-info/PKG-INFO
quickstep.egg-info/SOURCES.txt
quickstep.egg-info/dependency_links.txt
quickstep.egg-info/top_level.txt