Metadata-Version: 1.0
Name: quickstep
Version: 0.0.5
Summary: Quickstep GRPC API
Home-page: UNKNOWN
Author: Robert Claus
Author-email: robertclaus@gmail.com
License: Apache
Platform: UNKNOWN
